{
  "date": "10-ти септември",
  "meals": [
    {
      "name": "Козуначен мъфин с шоколад",
      "price": "1.20",
      "currency": "лв",
      "imageUrl": "https://bcvt.eu/sbf/bgerp/_tb_/c1573fd0-200.jpg",
      "ean": "2040",
      "weight": "200",
      "unit": "гр"
    },
    {
      "name": "Сандвич с кайма и кашкавал",
      "price": "4.00",
      "currency": "лв",
      "imageUrl": "https://bcvt.eu/sbf/bgerp/_tb_/78fca265-200.jpg",
      "ean": "2008",
      "weight": "200",
      "unit": "гр"
    },
    {
      "name": "Тутманик с пълнеж и заливка от сирене",
      "price": "4.00",
      "currency": "лв",
      "imageUrl": "https://bcvt.eu/sbf/bgerp/_tb_/174176fe-200.jpg",
      "ean": "2044",
      "weight": "150",
      "unit": "гр"
    },
    {
      "name": "Зелена салата с киноа",
      "price": "2.90",
      "currency": "лв",
      "imageUrl": "https://bcvt.eu/sbf/bgerp/_tb_/3a9e7d62-200.jpg",
      "ean": "4087",
      "weight": "150",
      "unit": "гр"
    },
    {
      "name": "Шопска салата",
      "price": "4.90",
      "currency": "лв",
      "imageUrl": "https://bcvt.eu/sbf/bgerp/_tb_/6e51fe27-200.jpg",
      "ean": "4001",
      "weight": "200",
      "unit": "гр"
    },
    {
      "name": "Зеленчукова крем супа",
      "price": "2.90",
      "currency": "лв",
      "imageUrl": "https://bcvt.eu/sbf/bgerp/_tb_/3edc4dd4-200.jpg",
      "ean": "5043",
      "weight": "300",
      "unit": "гр"
    },
    {
      "name": "Супа топчета",
      "price": "3.90",
      "currency": "лв",
      "imageUrl": "https://bcvt.eu/sbf/bgerp/_tb_/1427be83-200.jpg",
      "ean": "5004",
      "weight": "300",
      "unit": "гр"
    },
    {
      "name": "Бейби картофи с копър и чесън",
      "price": "3.00",
      "currency": "лв",
      "imageUrl": "https://bcvt.eu/sbf/bgerp/_tb_/ee32a32d-200.jpg",
      "ean": "6414",
      "weight": "200",
      "unit": "гр"
    },
    {
      "name": "Глазирани моркови",
      "price": "2.60",
      "currency": "лв",
      "imageUrl": "https://bcvt.eu/sbf/bgerp/_tb_/afb0f256-200.jpg",
      "ean": "6383",
      "weight": "150",
      "unit": "гр"
    },
    {
      "name": "Ориз с маслини и чери домат",
      "price": "3.20",
      "currency": "лв",
      "imageUrl": "https://bcvt.eu/sbf/bgerp/_tb_/78a662b8-200.jpg",
      "ean": "6415",
      "weight": "250",
      "unit": "гр"
    },
    {
      "name": "Парче пица със сирена",
      "price": "4.90",
      "currency": "лв",
      "imageUrl": "https://bcvt.eu/sbf/bgerp/_tb_/eee6a298-200.jpg",
      "ean": "6421",
      "weight": "250",
      "unit": "гр"
    },
    {
      "name": "Пилешко бутче на скара",
      "price": "6.00",
      "currency": "лв",
      "weight": "300",
      "unit": "гр"
    },
    {
      "name": "Сьомга филе на плоча",
      "price": "11.50",
      "currency": "лв",
      "imageUrl": "https://bcvt.eu/sbf/bgerp/_tb_/f2cad42f-200.jpg",
      "ean": "6530",
      "weight": "150",
      "unit": "гр"
    },
    {
      "name": "Телешко кебапче",
      "price": "2.80",
      "currency": "лв",
      "imageUrl": "https://bcvt.eu/sbf/bgerp/_tb_/238846b8-200.jpg",
      "ean": "6583",
      "weight": "80",
      "unit": "гр"
    },
    {
      "name": "Шницел от кайма",
      "price": "6.90",
      "currency": "лв",
      "imageUrl": "https://bcvt.eu/sbf/bgerp/_tb_/5df4e366-200.jpg",
      "ean": "6065",
      "weight": "200",
      "unit": "гр"
    },
    {
      "name": "Яхния от свинско месо и картофи",
      "price": "6.00",
      "currency": "лв",
      "imageUrl": "https://bcvt.eu/sbf/bgerp/_tb_/01cbadbe-200.jpg",
      "ean": "6245",
      "weight": "300",
      "unit": "гр"
    },
    {
      "name": "Диня",
      "price": "3.00",
      "currency": "лв",
      "imageUrl": "https://bcvt.eu/sbf/bgerp/_tb_/9f58ba8e-200.jpg",
      "ean": "8112",
      "weight": "300",
      "unit": "гр"
    },
    {
      "name": "Крем Брюле",
      "price": "4.90",
      "currency": "лв",
      "weight": "150",
      "unit": "гр"
    },
    {
      "name": "Крем Орео",
      "price": "3.90",
      "currency": "лв",
      "weight": "200",
      "unit": "гр"
    },
    {
      "name": "Крем карамел",
      "price": "2.50",
      "currency": "лв",
      "weight": "150",
      "unit": "гр"
    },
    {
      "name": "Крем с чия и бял шоколад",
      "price": "3.60",
      "currency": "лв",
      "weight": "150",
      "unit": "гр"
    },
    {
      "name": "Мини еклери",
      "price": "3.00",
      "currency": "лв",
      "weight": "170",
      "unit": "гр"
    },
    {
      "name": "Шоколадова торта",
      "price": "5.90",
      "currency": "лв",
      "weight": "150",
      "unit": "гр"
    },
    {
      "name": "Шоколадово брауни",
      "price": "3.00",
      "currency": "лв"
    }
  ]
}
