{
  "date": "10/12",
  "meals": [
    {
      "name": "Болярска закуска с кренвирш",
      "price": "4.00",
      "currency": "лв",
      "imageUrl": "https://bcvt.eu/sbf/bgerp/_tb_/3c900943-200.jpg",
      "ean": "2004",
      "weight": "190",
      "unit": "гр"
    },
    {
      "name": "Кроасан с масло",
      "price": "2.00",
      "currency": "лв",
      "imageUrl": "https://bcvt.eu/sbf/bgerp/_tb_/1256a571-200.jpg",
      "ean": "2016",
      "weight": "70",
      "unit": "гр"
    },
    {
      "name": "Овесена баница",
      "price": "1.90",
      "currency": "лв",
      "imageUrl": "https://bcvt.eu/sbf/bgerp/_tb_/69add327-200.jpg",
      "ean": "2048",
      "weight": "150",
      "unit": "гр"
    },
    {
      "name": "Домати с моцарела и босилково песто",
      "price": "6.10",
      "currency": "лв",
      "imageUrl": "https://bcvt.eu/sbf/bgerp/_tb_/a6c19764-200.jpg",
      "ean": "4003",
      "weight": "150",
      "unit": "гр"
    },
    {
      "name": "Салата с кус-кус, кис. краставици, маслини, шунка",
      "price": "4.20",
      "currency": "лв",
      "weight": "250",
      "unit": "гр"
    },
    {
      "name": "Салата снежанка",
      "price": "3.80",
      "currency": "лв",
      "imageUrl": "https://bcvt.eu/sbf/bgerp/_tb_/a22cd598-200.jpg",
      "ean": "4012",
      "weight": "150",
      "unit": "гр"
    },
    {
      "name": "Агнешка супа",
      "price": "5.30",
      "currency": "лв",
      "imageUrl": "https://bcvt.eu/sbf/bgerp/_tb_/762d386c-200.jpg",
      "ean": "5032",
      "weight": "300",
      "unit": "гр"
    },
    {
      "name": "Супа от диворастящи гъби",
      "price": "2.90",
      "currency": "лв",
      "imageUrl": "https://bcvt.eu/sbf/bgerp/_tb_/00bcd1c5-200.jpg",
      "ean": "5007",
      "weight": "300",
      "unit": "гр"
    },
    {
      "name": "Агнешко със спанак, гъби и ориз",
      "price": "9.50",
      "currency": "лв",
      "imageUrl": "https://bcvt.eu/sbf/bgerp/_tb_/78a8eb5b-200.jpg",
      "ean": "6078",
      "weight": "0.35",
      "unit": "гр"
    },
    {
      "name": "Задушени зеленчуци в масло",
      "price": "3.20",
      "currency": "лв",
      "imageUrl": "https://bcvt.eu/sbf/bgerp/_tb_/f9c143c0-200.png",
      "ean": "6088",
      "weight": "150",
      "unit": "гр"
    },
    {
      "name": "Запеканка от броколи с моцарела",
      "price": "6.50",
      "currency": "лв",
      "imageUrl": "https://bcvt.eu/sbf/bgerp/_tb_/3845317f-200.jpg",
      "ean": "6320",
      "weight": "300",
      "unit": "гр"
    },
    {
      "name": "Печени картофи",
      "price": "3.10",
      "currency": "лв",
      "imageUrl": "https://bcvt.eu/sbf/bgerp/_tb_/5aaa0c36-200.jpg",
      "ean": "6119",
      "weight": "200",
      "unit": "гр"
    },
    {
      "name": "Пиле по европейски",
      "price": "9.00",
      "currency": "лв",
      "weight": "300",
      "unit": "гр"
    },
    {
      "name": "Риба тон на плоча",
      "price": "12.50",
      "currency": "лв",
      "imageUrl": "https://bcvt.eu/sbf/bgerp/_tb_/72f0b86e-200.jpg",
      "ean": "6606",
      "weight": "150",
      "unit": "гр"
    },
    {
      "name": "Свинско шишче на скара",
      "price": "4.90",
      "currency": "лв",
      "imageUrl": "https://bcvt.eu/sbf/bgerp/_tb_/5c0a034e-200.jpg",
      "ean": "6077",
      "weight": "150",
      "unit": "гр"
    },
    {
      "name": "Скумрия в доматен сос",
      "price": "6.30",
      "currency": "лв",
      "imageUrl": "https://bcvt.eu/sbf/bgerp/_tb_/4647683a-200.jpg",
      "ean": "6124",
      "weight": "250",
      "unit": "гр"
    },
    {
      "name": "Спаначено кюфте със сирене",
      "price": "4.00",
      "currency": "лв",
      "imageUrl": "https://bcvt.eu/sbf/bgerp/_tb_/d3376e4e-200.jpg",
      "ean": "6314",
      "weight": "200",
      "unit": "гр"
    },
    {
      "name": "Телешко кебапче",
      "price": "2.80",
      "currency": "лв",
      "imageUrl": "https://bcvt.eu/sbf/bgerp/_tb_/238846b8-200.jpg",
      "ean": "6583",
      "weight": "80",
      "unit": "гр"
    },
    {
      "name": "Домашна бисквитена торта",
      "price": "3.20",
      "currency": "лв",
      "weight": "150",
      "unit": "гр"
    },
    {
      "name": "Крем Брюле",
      "price": "4.90",
      "currency": "лв",
      "weight": "150",
      "unit": "гр"
    },
    {
      "name": "Мини еклери",
      "price": "3.00",
      "currency": "лв",
      "weight": "170",
      "unit": "гр"
    },
    {
      "name": "Орехов крем",
      "price": "3.90",
      "currency": "лв"
    },
    {
      "name": "Салам торта",
      "price": "4.00",
      "currency": "лв",
      "weight": "150",
      "unit": "гр"
    },
    {
      "name": "Шоколадов мус",
      "price": "3.10",
      "currency": "лв",
      "weight": "150",
      "unit": "гр"
    },
    {
      "name": "Шоколадово брауни",
      "price": "3.00",
      "currency": "лв"
    },
    {
      "name": "Печена тиква",
      "price": "2.90",
      "currency": "лв",
      "weight": "200",
      "unit": "гр"
    }
  ]
}
